potato/__init__.py
potato/active_learning_manager.py
potato/admin.py
potato/agreement.py
potato/annotation_history.py
potato/authentication.py
potato/cli.py
potato/create_task_cli.py
potato/directory_watcher.py
potato/expertise_manager.py
potato/flask_server.py
potato/interaction_tracking.py
potato/item_state_management.py
potato/logging_config.py
potato/migrate_cli.py
potato/phase.py
potato/preview_cli.py
potato/quality_control.py
potato/remove_users_from_queue.py
potato/routes.py
potato/setup_multilingual_config.py
potato/setup_multitask_config.py
potato/user_state_management.py
potato/ai/__init__.py
potato/ai/ai_cache.py
potato/ai/ai_endpoint.py
potato/ai/ai_help_wrapper.py
potato/ai/ai_prompt.py
potato/ai/anthropic_endpoint.py
potato/ai/gemini_endpoint.py
potato/ai/huggingface_endpoint.py
potato/ai/icl_labeler.py
potato/ai/icl_prompt_builder.py
potato/ai/llm_active_learning.py
potato/ai/ollama_endpoint.py
potato/ai/openai_endpoint.py
potato/ai/openrouter_endpoint.py
potato/ai/vllm_endpoint.py
potato/database/__init__.py
potato/database/connection.py
potato/database/mysql_user_state.py
potato/server_utils/__init__.py
potato/server_utils/arg_utils.py
potato/server_utils/cli_utlis.py
potato/server_utils/config_module.py
potato/server_utils/front_end.py
potato/server_utils/html_sanitizer.py
potato/server_utils/json.py
potato/server_utils/mturk_apis.py
potato/server_utils/prolific_apis.py
potato/server_utils/waveform_service.py
potato/server_utils/schemas/__init__.py
potato/server_utils/schemas/audio_annotation.py
potato/server_utils/schemas/identifier_utils.py
potato/server_utils/schemas/image_annotation.py
potato/server_utils/schemas/likert.py
potato/server_utils/schemas/multirate.py
potato/server_utils/schemas/multiselect.py
potato/server_utils/schemas/number.py
potato/server_utils/schemas/pure_display.py
potato/server_utils/schemas/radio.py
potato/server_utils/schemas/registry.py
potato/server_utils/schemas/select.py
potato/server_utils/schemas/slider.py
potato_annotation-2.0.1.dist-info/licenses/LICENSE
potato_annotation-2.0.1.dist-info/METADATA
potato_annotation-2.0.1.dist-info/WHEEL
potato_annotation-2.0.1.dist-info/entry_points.txt
potato_annotation-2.0.1.dist-info/top_level.txt
potato_annotation-2.0.1.dist-info/RECORD
